{
  "schema": "coverage-map/v2",
  "sourceDocument": "SC102-2/26-2005F",
  "sourceText": "sources/text/OF26.txt",
  "objectiveId": "OF26",
  "ofNumber": 26,
  "titleFr": "Décrire des déplacements",
  "titleEn": "To describe movement",
  "grammarConcepts": [
    "pronouns",
    "passe_compose"
  ],
  "sections": [
    {
      "id": "26.1",
      "heading": "Notions",
      "topicsFr": "",
      "kind": "vocabulary",
      "covered": true,
      "itemCount": 63,
      "linkedItems": [
        "itm_of26_voc_fe_1",
        "itm_of26_voc_fe_2",
        "itm_of26_voc_fe_3",
        "itm_of26_voc_fe_4",
        "itm_of26_voc_fe_5",
        "itm_of26_voc_fe_6",
        "itm_of26_voc_fe_7",
        "itm_of26_voc_fe_8"
      ]
    },
    {
      "id": "26.2",
      "heading": "Grammaire",
      "topicsFr": "",
      "kind": "grammar",
      "covered": true,
      "itemCount": 161,
      "linkedItems": [
        "itm_of26_src_a4_1",
        "itm_of26_src_a4_2",
        "itm_of26_src_a4_3",
        "itm_of26_src_a4_4",
        "itm_of26_src_a4_5",
        "itm_of26_src_a4_6",
        "itm_of26_src_a4_7",
        "itm_of26_src_a4_8"
      ]
    },
    {
      "id": "26.3",
      "heading": "Fonctions",
      "topicsFr": "",
      "kind": "function",
      "covered": false,
      "itemCount": 0,
      "linkedItems": []
    },
    {
      "id": "26.4",
      "heading": "Fonctions",
      "topicsFr": "",
      "kind": "function",
      "covered": false,
      "itemCount": 0,
      "linkedItems": []
    }
  ],
  "vocabulary": {
    "source": "Lexique OF26 (SC102-2/1-2-2005F)",
    "entries": 41,
    "questions": 63,
    "convertible": true,
    "covered": true
  },
  "examples": {
    "sourceMarkers": 2,
    "derivedItems": 161,
    "convertible": true,
    "covered": true,
    "note": "model sentences are embedded in the section text; their patterns are practised through the grammar/transform items derived from this OF"
  },
  "selfTest": {
    "selfEvalBooklet": "selfeval-3 (SC102-2-45-3)",
    "consolidationBooklet": "consolidation-3 (SC102-2-47-3)",
    "convertible": true,
    "extracted": false,
    "covered": false,
    "note": "Cloze self-test passages with answer keys exist in the range booklet but use a numbered-(N)-blank format and are not yet extracted into items — actionable gap."
  },
  "activities": [
    {
      "activity": 1,
      "hasAnswerKey": false,
      "convertible": false,
      "extracted": false,
      "itemCount": 0,
      "linkedItems": []
    },
    {
      "activity": 2,
      "hasAnswerKey": false,
      "convertible": false,
      "extracted": false,
      "itemCount": 0,
      "linkedItems": []
    },
    {
      "activity": 3,
      "hasAnswerKey": false,
      "convertible": false,
      "extracted": false,
      "itemCount": 0,
      "linkedItems": []
    },
    {
      "activity": 4,
      "hasAnswerKey": true,
      "convertible": true,
      "extracted": true,
      "itemCount": 8,
      "linkedItems": [
        "itm_of26_src_a4_1",
        "itm_of26_src_a4_2",
        "itm_of26_src_a4_3",
        "itm_of26_src_a4_4",
        "itm_of26_src_a4_5",
        "itm_of26_src_a4_6",
        "itm_of26_src_a4_7",
        "itm_of26_src_a4_8"
      ]
    },
    {
      "activity": 5,
      "hasAnswerKey": true,
      "convertible": true,
      "extracted": true,
      "itemCount": 10,
      "linkedItems": [
        "itm_of26_src_a5_1",
        "itm_of26_src_a5_2",
        "itm_of26_src_a5_3",
        "itm_of26_src_a5_4",
        "itm_of26_src_a5_5",
        "itm_of26_src_a5_6",
        "itm_of26_src_a5_7",
        "itm_of26_src_a5_8",
        "itm_of26_src_a5_9",
        "itm_of26_src_a5_10"
      ]
    },
    {
      "activity": 6,
      "hasAnswerKey": false,
      "convertible": false,
      "extracted": false,
      "itemCount": 0,
      "linkedItems": []
    },
    {
      "activity": 7,
      "hasAnswerKey": true,
      "convertible": true,
      "extracted": true,
      "itemCount": 10,
      "linkedItems": [
        "itm_of26_src_a7_1",
        "itm_of26_src_a7_2",
        "itm_of26_src_a7_3",
        "itm_of26_src_a7_4",
        "itm_of26_src_a7_5",
        "itm_of26_src_a7_6",
        "itm_of26_src_a7_7",
        "itm_of26_src_a7_8",
        "itm_of26_src_a7_9",
        "itm_of26_src_a7_10"
      ]
    },
    {
      "activity": 8,
      "hasAnswerKey": true,
      "convertible": true,
      "extracted": true,
      "itemCount": 25,
      "linkedItems": [
        "itm_of26_src_a8_1",
        "itm_of26_src_a8_2",
        "itm_of26_src_a8_3",
        "itm_of26_src_a8_4",
        "itm_of26_src_a8_5",
        "itm_of26_src_a8_6",
        "itm_of26_src_a8_7",
        "itm_of26_src_a8_8",
        "itm_of26_src_a8_9",
        "itm_of26_src_a8_10",
        "itm_of26_src_a8_11",
        "itm_of26_src_a8_12",
        "itm_of26_src_a8_13",
        "itm_of26_src_a8_14",
        "itm_of26_src_a8_15",
        "itm_of26_src_a8_16",
        "itm_of26_src_a8_17",
        "itm_of26_src_a8_18",
        "itm_of26_src_a8_19",
        "itm_of26_src_a8_20",
        "itm_of26_src_a8_21",
        "itm_of26_src_a8_22",
        "itm_of26_src_a8_23",
        "itm_of26_src_a8_24",
        "itm_of26_src_a8_25"
      ]
    },
    {
      "activity": 9,
      "hasAnswerKey": false,
      "convertible": false,
      "extracted": false,
      "itemCount": 0,
      "linkedItems": []
    },
    {
      "activity": 10,
      "hasAnswerKey": true,
      "convertible": true,
      "extracted": true,
      "itemCount": 10,
      "linkedItems": [
        "itm_of26_src_a10_1",
        "itm_of26_src_a10_2",
        "itm_of26_src_a10_3",
        "itm_of26_src_a10_4",
        "itm_of26_src_a10_5",
        "itm_of26_src_a10_6",
        "itm_of26_src_a10_7",
        "itm_of26_src_a10_8",
        "itm_of26_src_a10_9",
        "itm_of26_src_a10_10"
      ]
    },
    {
      "activity": 11,
      "hasAnswerKey": true,
      "convertible": true,
      "extracted": true,
      "itemCount": 12,
      "linkedItems": [
        "itm_of26_src_a11_1",
        "itm_of26_src_a11_2",
        "itm_of26_src_a11_3",
        "itm_of26_src_a11_4",
        "itm_of26_src_a11_5",
        "itm_of26_src_a11_6",
        "itm_of26_src_a11_7",
        "itm_of26_src_a11_8",
        "itm_of26_src_a11_9",
        "itm_of26_src_a11_10",
        "itm_of26_src_a11_11",
        "itm_of26_src_a11_12"
      ]
    },
    {
      "activity": 12,
      "hasAnswerKey": true,
      "convertible": true,
      "extracted": true,
      "itemCount": 11,
      "linkedItems": [
        "itm_of26_src_a12_1",
        "itm_of26_src_a12_2",
        "itm_of26_src_a12_3",
        "itm_of26_src_a12_4",
        "itm_of26_src_a12_5",
        "itm_of26_src_a12_6",
        "itm_of26_src_a12_7",
        "itm_of26_src_a12_8",
        "itm_of26_src_a12_9",
        "itm_of26_src_a12_10",
        "itm_of26_src_a12_11"
      ]
    },
    {
      "activity": 13,
      "hasAnswerKey": true,
      "convertible": true,
      "extracted": true,
      "itemCount": 15,
      "linkedItems": [
        "itm_of26_src_a13_1",
        "itm_of26_src_a13_2",
        "itm_of26_src_a13_3",
        "itm_of26_src_a13_4",
        "itm_of26_src_a13_5",
        "itm_of26_src_a13_6",
        "itm_of26_src_a13_7",
        "itm_of26_src_a13_8",
        "itm_of26_src_a13_9",
        "itm_of26_src_a13_10",
        "itm_of26_src_a13_11",
        "itm_of26_src_a13_12",
        "itm_of26_src_a13_13",
        "itm_of26_src_a13_14",
        "itm_of26_src_a13_15"
      ]
    },
    {
      "activity": 14,
      "hasAnswerKey": false,
      "convertible": false,
      "extracted": false,
      "itemCount": 0,
      "linkedItems": []
    },
    {
      "activity": 15,
      "hasAnswerKey": true,
      "convertible": true,
      "extracted": true,
      "itemCount": 11,
      "linkedItems": [
        "itm_of26_src_a15_2",
        "itm_of26_src_a15_3",
        "itm_of26_src_a15_4",
        "itm_of26_src_a15_5",
        "itm_of26_src_a15_6",
        "itm_of26_src_a15_7",
        "itm_of26_src_a15_8",
        "itm_of26_src_a15_9",
        "itm_of26_src_a15_10",
        "itm_of26_src_a15_11",
        "itm_of26_src_a15_12"
      ]
    },
    {
      "activity": 16,
      "hasAnswerKey": true,
      "convertible": true,
      "extracted": true,
      "itemCount": 15,
      "linkedItems": [
        "itm_of26_src_a16_1",
        "itm_of26_src_a16_2",
        "itm_of26_src_a16_3",
        "itm_of26_src_a16_4",
        "itm_of26_src_a16_5",
        "itm_of26_src_a16_6",
        "itm_of26_src_a16_7",
        "itm_of26_src_a16_8",
        "itm_of26_src_a16_9",
        "itm_of26_src_a16_10",
        "itm_of26_src_a16_11",
        "itm_of26_src_a16_12",
        "itm_of26_src_a16_13",
        "itm_of26_src_a16_14",
        "itm_of26_src_a16_15"
      ]
    },
    {
      "activity": 17,
      "hasAnswerKey": true,
      "convertible": true,
      "extracted": true,
      "itemCount": 12,
      "linkedItems": [
        "itm_of26_src_a17_1",
        "itm_of26_src_a17_2",
        "itm_of26_src_a17_3",
        "itm_of26_src_a17_4",
        "itm_of26_src_a17_5",
        "itm_of26_src_a17_6",
        "itm_of26_src_a17_7",
        "itm_of26_src_a17_8",
        "itm_of26_src_a17_9",
        "itm_of26_src_a17_10",
        "itm_of26_src_a17_11",
        "itm_of26_src_a17_12"
      ]
    },
    {
      "activity": 18,
      "hasAnswerKey": true,
      "convertible": true,
      "extracted": true,
      "itemCount": 12,
      "linkedItems": [
        "itm_of26_src_a18_1",
        "itm_of26_src_a18_2",
        "itm_of26_src_a18_3",
        "itm_of26_src_a18_4",
        "itm_of26_src_a18_5",
        "itm_of26_src_a18_6",
        "itm_of26_src_a18_7",
        "itm_of26_src_a18_8",
        "itm_of26_src_a18_9",
        "itm_of26_src_a18_10",
        "itm_of26_src_a18_11",
        "itm_of26_src_a18_12"
      ]
    },
    {
      "activity": 19,
      "hasAnswerKey": true,
      "convertible": true,
      "extracted": true,
      "itemCount": 10,
      "linkedItems": [
        "itm_of26_src_a19_1",
        "itm_of26_src_a19_2",
        "itm_of26_src_a19_3",
        "itm_of26_src_a19_4",
        "itm_of26_src_a19_5",
        "itm_of26_src_a19_6",
        "itm_of26_src_a19_7",
        "itm_of26_src_a19_8",
        "itm_of26_src_a19_9",
        "itm_of26_src_a19_10"
      ]
    },
    {
      "activity": 20,
      "hasAnswerKey": false,
      "convertible": false,
      "extracted": false,
      "itemCount": 0,
      "linkedItems": []
    },
    {
      "activity": 21,
      "hasAnswerKey": false,
      "convertible": false,
      "extracted": false,
      "itemCount": 0,
      "linkedItems": []
    },
    {
      "activity": 22,
      "hasAnswerKey": false,
      "convertible": false,
      "extracted": false,
      "itemCount": 0,
      "linkedItems": []
    },
    {
      "activity": 23,
      "hasAnswerKey": false,
      "convertible": false,
      "extracted": false,
      "itemCount": 0,
      "linkedItems": []
    },
    {
      "activity": 24,
      "hasAnswerKey": false,
      "convertible": false,
      "extracted": false,
      "itemCount": 0,
      "linkedItems": []
    }
  ],
  "validation": {
    "strictComplete": false,
    "convertibleComplete": false,
    "totalElements": 31,
    "coveredElements": 17,
    "convertible": {
      "covered": 17,
      "total": 18
    },
    "actionableGaps": {
      "sections": [],
      "activities": [],
      "vocabulary": [],
      "examples": [],
      "selfTest": [
        "selfeval-3 (SC102-2-45-3)"
      ]
    },
    "nonConvertible": {
      "sections": [
        "26.3 Fonctions (function)",
        "26.4 Fonctions (function)"
      ],
      "activities": [
        1,
        2,
        3,
        6,
        9,
        14,
        20,
        21,
        22,
        23,
        24
      ]
    },
    "note": "strictComplete requires a learning item for EVERY source element. Oral/strategy/phonetic sections and activities without a published answer key cannot become auto-gradable questions, so they are flagged under nonConvertible and keep strictComplete=false. convertibleComplete tracks the actionable target: every answer-keyed activity, grammar section, and the lexicon turned into items."
  }
}